devor/__init__.py
devor-0.0.1.dist-info/METADATA
devor-0.0.1.dist-info/WHEEL
devor-0.0.1.dist-info/RECORD
