Metadata-Version: 2.1
Name: devor
Version: 0.0.1
Summary: Container-based development environment manager, inspired by conda.
License: Apache2
Author: Hugh Jiang
Author-email: jjqzy@foxmail.com
Requires-Python: >=3.10,<4.0
Classifier: License :: Other/Proprietary License
Classifier: Programming Language :: Python :: 3
Classifier: Programming Language :: Python :: 3.10
Classifier: Programming Language :: Python :: 3.11
Classifier: Programming Language :: Python :: 3.12
Requires-Dist: requests (>=2.23.0,<3.0.0)
